scryfall_mcp/__init__.py
scryfall_mcp/__main__.py
scryfall_mcp/db_bulk_operations.py
scryfall_mcp/db_manager.py
scryfall_mcp/db_utils.py
scryfall_mcp/scryfall_art_download.py
scryfall_mcp/scryfall_card_download.py
scryfall_mcp/scryfall_search.py
scryfall_mcp/server.py
scryfall_mcp-0.0.4.dist-info/METADATA
scryfall_mcp-0.0.4.dist-info/WHEEL
scryfall_mcp-0.0.4.dist-info/entry_points.txt
scryfall_mcp-0.0.4.dist-info/RECORD
