Metadata-Version: 2.4
Name: scryfall-mcp
Version: 0.0.4
Summary: A Model Context Protocol (MCP) server that provides access to the Scryfall API for Magic: The Gathering card data.
Project-URL: Homepage, https://github.com/kaminaduck/scryfall-mcp
Project-URL: Repository, https://github.com/kaminaduck/scryfall-mcp
Project-URL: Issues, https://github.com/kaminaduck/scryfall-mcp/issues
Author-email: Charlie Rogers <charlie.rogers@fearnworks.com>
License: Apache-2.0
Keywords: api,cards,magic-the-gathering,mcp,mtg,scryfall
Classifier: Development Status :: 4 - Beta
Classifier: Intended Audience :: Developers
Classifier: License :: OSI Approved :: Apache Software License
Classifier: Programming Language :: Python :: 3
Classifier: Programming Language :: Python :: 3.12
Classifier: Topic :: Games/Entertainment
Classifier: Topic :: Software Development :: Libraries :: Python Modules
Requires-Python: >=3.12
Requires-Dist: build>=1.2.2.post1
Requires-Dist: httpx>=0.28.1
Requires-Dist: mcp[cli]>=1.8.0
Requires-Dist: twine>=6.1.0
Provides-Extra: dev
Requires-Dist: pytest>=7.4.0; extra == 'dev'
